{
  "project_info": {
    "project_number": "1097912803730",
    "project_id": "trainner-app-1b230",
    "storage_bucket": "trainner-app-1b230.firebasestorage.app"
  },
  "client": [
    {
      "client_info": {
        "mobilesdk_app_id": "1:1097912803730:android:b4615d85383e5349ba614b",
        "android_client_info": {
          "package_name": "com.company.trainnerapp"
        }
      },
      "oauth_client": [],
      "api_key": [
        {
          "current_key": "AIzaSyDg0c9peN9YuGLHIE0usJU_u6JLebgChJE"
        }
      ],
      "services": {
        "appinvite_service": {
          "other_platform_oauth_client": []
        }
      }
    }
  ],
  "configuration_version": "1"
}